[{"id": 1, "username": "Anonymous", "text": "Good experience using this website", "rating": 4, "date": "2026-02-06T13:27:14"}, {"id": 2, "username": "Anonymous", "text": "Good Treatment and getting result clearly", "rating": 5, "date": "2026-02-09T13:11:26"}, {"id": 3, "username": "Anonymous", "text": "good", "rating": 4, "date": "2026-02-09T13:37:34"}, {"id": 4, "username": "Anonymous", "text": "Good Experience", "rating": 5, "date": "2026-02-15T05:20:13"}, {"id": 5, "username": "Bhagya", "text": "Good\n", "rating": 4, "date": "2026-04-09T17:46:36"}]